gdelt_process_tone.py
gdelt_process_tone-0.0.13.data/data/v2_events_schema.csv
gdelt_process_tone-0.0.13.dist-info/DESCRIPTION.rst
gdelt_process_tone-0.0.13.dist-info/METADATA
gdelt_process_tone-0.0.13.dist-info/RECORD
gdelt_process_tone-0.0.13.dist-info/WHEEL
gdelt_process_tone-0.0.13.dist-info/metadata.json
gdelt_process_tone-0.0.13.dist-info/top_level.txt
