Metadata-Version: 2.0
Name: gdelt-process-tone
Version: 0.0.13
Summary: Returns tone and location json files
Home-page: UNKNOWN
Author: Development Seed
Author-email: aimee@developmentseed.org
License: MIT
Platform: UNKNOWN
